hox/__init__.py
hox/hox.py
hox/utils.py
hox-1.2.0.dist-info/METADATA
hox-1.2.0.dist-info/WHEEL
hox-1.2.0.dist-info/top_level.txt
hox-1.2.0.dist-info/RECORD
